setup.py
pyPostal.egg-info/PKG-INFO
pyPostal.egg-info/SOURCES.txt
pyPostal.egg-info/dependency_links.txt
pyPostal.egg-info/not-zip-safe
pyPostal.egg-info/top_level.txt
pypostal/__init__.py
pypostal/pixelletter.py
pypostal/sipgate.py