Metadata-Version: 1.0
Name: pyPostal
Version: 1.1
Summary: pyPostal is an Interface for sending real (paper-based) letters via API (Pixelletter)
Home-page: http://github.com/hudora/pyPostal/#readme
Author: Maximillian Dornseif
Author-email: md@hudora.de
License: BSD
Platform: UNKNOWN
Classifier: Intended Audience :: Developers
Classifier: Programming Language :: Python
